pysign/__init__.py
pysign/__main__.py
pysign/_cli.py
pysign/_version.py
test/__init__.py
test/test_version.py
pysign-0.0.1rc0.dist-info/LICENSE
pysign-0.0.1rc0.dist-info/METADATA
pysign-0.0.1rc0.dist-info/WHEEL
pysign-0.0.1rc0.dist-info/entry_points.txt
pysign-0.0.1rc0.dist-info/top_level.txt
pysign-0.0.1rc0.dist-info/RECORD
